MANIFEST.in
README.rst
ez_setup.py
redisbayes.py
setup.py
redisbayes.egg-info/PKG-INFO
redisbayes.egg-info/SOURCES.txt
redisbayes.egg-info/dependency_links.txt
redisbayes.egg-info/requires.txt
redisbayes.egg-info/top_level.txt