Metadata-Version: 1.0
Name: redisbayes
Version: 0.1.3
Summary: Naïve Bayesian Text Classifier on Redis
Home-page: https://github.com/jart/redisbayes
Author: Justine Tunney
Author-email: jtunney@lobstertech.com
License: MIT
Platform: UNKNOWN
Classifier: Development Status :: 5 - Production/Stable
Classifier: License :: OSI Approved :: MIT License
Classifier: Intended Audience :: Developers
Classifier: Programming Language :: Python
Classifier: Topic :: Database
Classifier: Topic :: Communications :: Email
